[
   {
      "objectGuid": "agYOXVSJhCYeQ4QocEKMqk",
      "objectName": "CI_CD_DEVELOPMENT",
      "objectType": "Project",
      "path": "/Explore",
      "metadata": {
         "additionalInfo": {
            "contentType": "Binary",
            "description": "Project to show CI/CD Pipeline",
            "documentState": "COMPLETE"
         },
         "contextAttributes": [],
         "modelVersion": {
            "major": 0,
            "minor": 0
         },
         "objectRefs": [],
         "repoInfo": null
      }
   }
]
